hpoflow/__init__.py
hpoflow/mlflow.py
hpoflow/optuna.py
hpoflow/optuna_mlflow.py
hpoflow/optuna_transformers.py
hpoflow/utils.py
hpoflow-0.1.4.dist-info/LICENSE
hpoflow-0.1.4.dist-info/METADATA
hpoflow-0.1.4.dist-info/WHEEL
hpoflow-0.1.4.dist-info/top_level.txt
hpoflow-0.1.4.dist-info/RECORD
